Metadata-Version: 1.0
Name: simple-profanity-filter
Version: 1.1.2
Summary: Simple profanity filtration.
Home-page: UNKNOWN
Author: UNKNOWN
Author-email: kirill.tim.020708@mail.ru
License: UNKNOWN
Platform: UNKNOWN
